README.rst
_description.org
lh-agpl3-LICENSE.txt
pyproject.toml
setup.py
bin/cmdbCntnrRepo.cs
bin/cmdbCntnrVMs.cs
bin/cmdbSiteCntnrs.cs
bisos/__init__.py
bisos.cmdb.egg-info/PKG-INFO
bisos.cmdb.egg-info/SOURCES.txt
bisos.cmdb.egg-info/dependency_links.txt
bisos.cmdb.egg-info/not-zip-safe
bisos.cmdb.egg-info/requires.txt
bisos.cmdb.egg-info/top_level.txt
bisos/cmdb/__init__.py
bisos/cmdb/cmdbCntnrRepo.py
bisos/cmdb/cmdbCntnrVMs.py
bisos/cmdb/cmdbSiteCntnrs.py